banner_manggee/__init__.py
banner_manggee/banner.py
banner_manggee-0.2.4.dist-info/METADATA
banner_manggee-0.2.4.dist-info/WHEEL
banner_manggee-0.2.4.dist-info/entry_points.txt
banner_manggee-0.2.4.dist-info/top_level.txt
banner_manggee-0.2.4.dist-info/RECORD
