Metadata-Version: 2.1
Name: banner_manggee
Version: 0.2.4
Summary: Banner Output Program
Author-email: mangG907 <mang.gee@gmail.com>
License: MIT
Project-URL: Homepage, https://github.com/mangG907/banner_manggee
Project-URL: Issues, https://github.com/mangG907/banner_manggee/issues
Requires-Python: >=3.9
Requires-Dist: pyfiglet >=1.0.2
